discord_oauth2_py-1.2.2.dist-info/licenses/LICENSE
discordoauth2/__init__.py
discordoauth2/async_oauth.py
discordoauth2/exceptions.py
discordoauth2/sync_oauth.py
discord_oauth2_py-1.2.2.dist-info/METADATA
discord_oauth2_py-1.2.2.dist-info/WHEEL
discord_oauth2_py-1.2.2.dist-info/top_level.txt
discord_oauth2_py-1.2.2.dist-info/RECORD
