Metadata-Version: 2.4
Name: discord-oauth2.py
Version: 1.2.2
Summary: Use Discord's OAuth2 effortlessly! Turns the auth code to a access token and the access token into scope infomation. 
Home-page: https://github.com/treeben77/discordoauth2
Author: TreeBen77
License: MIT
Keywords: flask,oauth2,discord,discord-api
Requires-Python: >=3.8
License-File: LICENSE
Requires-Dist: aiohttp
Requires-Dist: requests
Dynamic: author
Dynamic: description
Dynamic: description-content-type
Dynamic: home-page
Dynamic: keywords
Dynamic: license
Dynamic: license-file
Dynamic: requires-dist
Dynamic: requires-python
Dynamic: summary
